mrq/__init__.py
mrq/agent.py
mrq/config.py
mrq/context.py
mrq/exceptions.py
mrq/helpers.py
mrq/job.py
mrq/logger.py
mrq/monkey.py
mrq/processes.py
mrq/queue.py
mrq/queue_raw.py
mrq/queue_regular.py
mrq/redishelpers.py
mrq/scheduler.py
mrq/subpool.py
mrq/supervisor.py
mrq/task.py
mrq/utils.py
mrq/version.py
mrq/worker.py
mrq/basetasks/__init__.py
mrq/basetasks/cleaning.py
mrq/basetasks/indexes.py
mrq/basetasks/orchestrator.py
mrq/basetasks/utils.py
mrq/bin/__init__.py
mrq/bin/mrq_agent.py
mrq/bin/mrq_run.py
mrq/bin/mrq_worker.py
mrq/dashboard/__init__.py
mrq/dashboard/app.py
mrq/dashboard/utils.py
mrq/dashboard/static/package.json
mrq/dashboard/static/webpack.config.js
mrq/dashboard/static/bin/0.bundle.js
mrq/dashboard/static/bin/32941d6330044744c02493835b799e90.svg
mrq/dashboard/static/bin/64f2d23d70cb2b2810031880f554b13c.png
mrq/dashboard/static/bin/68ed1dac06bf0409c18ae7bc62889170.woff
mrq/dashboard/static/bin/6c56b94fd0540844a7118cdff565b0ae.png
mrq/dashboard/static/bin/7ad17c6085dee9a33787bac28fb23d46.eot
mrq/dashboard/static/bin/8f88d990024975797f96ce7648dacd2f.png
mrq/dashboard/static/bin/94b34ff5224ba38210d67623bb1a1504.png
mrq/dashboard/static/bin/bundle.js
mrq/dashboard/static/bin/d48475e6c742940f44e62622e16865b9.png
mrq/dashboard/static/bin/e49d52e74b7689a0727def99da31f3eb.ttf
mrq/dashboard/static/css/bootstrap-theme.min.css
mrq/dashboard/static/css/datatables.css
mrq/dashboard/static/css/jquery.circliful.css
mrq/dashboard/static/css/mrq-dashboard.css
mrq/dashboard/static/fonts/glyphicons-halflings-regular.eot
mrq/dashboard/static/fonts/glyphicons-halflings-regular.svg
mrq/dashboard/static/fonts/glyphicons-halflings-regular.ttf
mrq/dashboard/static/fonts/glyphicons-halflings-regular.woff
mrq/dashboard/static/images/favicon-old.ico
mrq/dashboard/static/images/favicon.ico
mrq/dashboard/static/images/sort_asc.png
mrq/dashboard/static/images/sort_asc_disabled.png
mrq/dashboard/static/images/sort_both.png
mrq/dashboard/static/images/sort_desc.png
mrq_custom-0.9.21.dist-info/LICENSE
mrq_custom-0.9.21.dist-info/METADATA
mrq_custom-0.9.21.dist-info/WHEEL
mrq_custom-0.9.21.dist-info/entry_points.txt
mrq_custom-0.9.21.dist-info/top_level.txt
mrq_custom-0.9.21.dist-info/RECORD
