Metadata-Version: 2.1
Name: mrq-custom
Version: 0.9.21
Summary: A simple yet powerful distributed worker task queue in Python
Home-page: http://github.com/pricingassistant/mrq
Author: Pricing Assistant
Author-email: contact@pricingassistant.com
License: MIT
Keywords: worker,task,distributed,queue,asynchronous,redis,mongodb,job,processing,gevent
Platform: any
Classifier: Programming Language :: Python
Classifier: Programming Language :: Python :: 2.7
Classifier: Programming Language :: Python :: 3.4
Classifier: Programming Language :: Python :: 3.5
Classifier: Programming Language :: Python :: 3.6
Classifier: Programming Language :: Python :: 3.7
Classifier: Development Status :: 5 - Production/Stable
Classifier: Environment :: Other Environment
Classifier: Intended Audience :: Developers
Classifier: License :: OSI Approved :: MIT License
Classifier: Operating System :: OS Independent
Classifier: Topic :: Utilities
Requires-Dist: argparse (>=1.1)
Requires-Dist: redis (==2.10.6)
Requires-Dist: pymongo (>=3.0.1)
Requires-Dist: gevent (>=1.2.2)
Requires-Dist: ujson (>=1.33)
Requires-Dist: hiredis (>=0.1.5)
Requires-Dist: psutil (<6.0,>=5.1.2)
Requires-Dist: objgraph (>=1.8.1)
Requires-Dist: termcolor (>=1.1.0)
Requires-Dist: future (>=0.15.2)
Requires-Dist: hiro (==0.5)
Requires-Dist: Flask (>=0.11.1)
